choicedesign/.DS_Store
choicedesign/__init__.py
choicedesign/algorithms.py
choicedesign/criteria.py
choicedesign/design.py
choicedesign/utils.py
choicedesign-0.1.6.dist-info/WHEEL
choicedesign-0.1.6.dist-info/METADATA
choicedesign-0.1.6.dist-info/RECORD
