Metadata-Version: 2.1
Name: choicedesign
Version: 0.1.6
Summary: Experimental designs for discrete choice models.
Author: José Ignacio Hernández
Author-email: joseignaciohernandezh@gmail.com
Requires-Python: >=3.8,<4.0
Classifier: Programming Language :: Python :: 3
Classifier: Programming Language :: Python :: 3.10
Classifier: Programming Language :: Python :: 3.8
Classifier: Programming Language :: Python :: 3.9
Requires-Dist: biogeme (>=3.2,<4.0)
Requires-Dist: numpy (>=1.23.4,<2.0.0)
Requires-Dist: pandas (>=1.5.1,<2.0.0)
